langpack/__init__.py
langpack/apis.py
langpack/app_template.py
langpack/chatbot_ui_backend_template.py
langpack/client_template.py
langpack/index.html
langpack/slack_backend_template.py
langpack/tester.py
langpack/tools.py
langpack/utils.py
langpack-0.0.12.dist-info/METADATA
langpack-0.0.12.dist-info/WHEEL
langpack-0.0.12.dist-info/entry_points.txt
langpack-0.0.12.dist-info/RECORD
